Metadata-Version: 2.1
Name: pacoteexercicio
Version: 0.0.1
Summary: Pacote python
Home-page: https://github.com/marcos-de-sousa/pacotepypi
Author: João cardoso
Author-email: jvcq13@gmail.com
License: MIT License
Keywords: Pacote
Platform: UNKNOWN
